multiple_inference/__init__.py
multiple_inference/base.py
multiple_inference/confidence_set.py
multiple_inference/rank_condition.py
multiple_inference/significance_condition.py
multiple_inference/stats.py
multiple_inference/utils.py
multiple_inference/bayes/__init__.py
multiple_inference/bayes/base.py
multiple_inference/bayes/improper.py
multiple_inference/bayes/nonparametric.py
multiple_inference/bayes/normal.py
multiple_inference-1.2.0.dist-info/LICENSE
multiple_inference-1.2.0.dist-info/METADATA
multiple_inference-1.2.0.dist-info/WHEEL
multiple_inference-1.2.0.dist-info/top_level.txt
multiple_inference-1.2.0.dist-info/RECORD
