Metadata-Version: 2.1
Name: multiple-inference
Version: 1.2.0
Summary: A statistics package for comparing multiple parameters.
Home-page: https://dsbowen.gitlab.io/conditional-inference
Author: Dillon Bowen
Author-email: dsbowen@wharton.upenn.edu
Classifier: Programming Language :: Python :: 3
Classifier: License :: OSI Approved :: MIT License
Classifier: Operating System :: OS Independent
Requires-Python: >=3.8
License-File: LICENSE
Requires-Dist: matplotlib (>=3.4)
Requires-Dist: numpy (>=1.20)
Requires-Dist: scikit-learn (>=1.0.2)
Requires-Dist: scipy (>=1.6)
Requires-Dist: seaborn (>=0.11.1)
Requires-Dist: statsmodels (>=0.12)
Requires-Dist: typing-extensions (>=3.10.0.0)
